astroquery_cli/__init__.py
astroquery_cli/i18n.py
astroquery_cli/main.py
astroquery_cli/modules/alma_cli.py
astroquery_cli/modules/esasky_cli.py
astroquery_cli/modules/gaia_cli.py
astroquery_cli/modules/irsa_cli.py
astroquery_cli/modules/irsa_dust_cli.py
astroquery_cli/modules/jplhorizons_cli.py
astroquery_cli/modules/jplsbdb_cli.py
astroquery_cli/modules/mast_cli.py
astroquery_cli/modules/nasa_ads_cli.py
astroquery_cli/modules/ned_cli.py
astroquery_cli/modules/simbad_cli.py
astroquery_cli/modules/splatalogue_cli.py
astroquery_cli/modules/vizier_cli.py
astroquery_cli/options/field.py
astroquery_cli/options/ping.py
astroquery_cli/options/test.py
astroquery_cli/utils.py
locales/fr/LC_MESSAGES/messages.mo
locales/ja/LC_MESSAGES/messages.mo
locales/zh/LC_MESSAGES/messages.mo
astroquery_cli-1.3.6.dist-info/METADATA
astroquery_cli-1.3.6.dist-info/WHEEL
astroquery_cli-1.3.6.dist-info/entry_points.txt
astroquery_cli-1.3.6.dist-info/RECORD
