Metadata-Version: 2.3
Name: astroquery_cli
Version: 1.3.6
Summary: CLI for astroquery modules with autocompletion.
Author: inoribea
Author-email: inoribea@outlook.com
Requires-Python: >=3.10,<4.0
Classifier: Programming Language :: Python :: 3
Classifier: Programming Language :: Python :: 3.10
Classifier: Programming Language :: Python :: 3.11
Classifier: Programming Language :: Python :: 3.12
Classifier: Programming Language :: Python :: 3.13
Requires-Dist: astropy (>=6.1.0,<7.0.0)
Requires-Dist: astroquery (>=0.4.10,<0.5.0)
Requires-Dist: babel (>=2.15.0,<3.0.0)
Requires-Dist: requests (>=2.10.0,<3.0.0)
Requires-Dist: rich (>=13.5.2,<14.0.0)
Requires-Dist: typer (>=0.15.4,<0.16.0)
